Librarymu/__init__.py
Librarymu/my_class.py
gold33423308/__init__.py
gold33423308/gold.py
gold33423308-4.0.dist-info/METADATA
gold33423308-4.0.dist-info/WHEEL
gold33423308-4.0.dist-info/top_level.txt
gold33423308-4.0.dist-info/RECORD
